cookiecutter_x/__init__.py
cookiecutter_x/cli.py
cookiecutter_x/cookiecutter_templates.py
cookiecutter_x/core.py
cookiecutter_x/main.py
cookiecutter_x/quick_start.py
cookiecutter_x/simple_templates.py
cookiecutter_x/template_processor.py
cookiecutter_x/utils.py
cookiecutter_x/extensions/__init__.py
cookiecutter_x-0.1.4.dist-info/LICENSE.txt
cookiecutter_x-0.1.4.dist-info/METADATA
cookiecutter_x-0.1.4.dist-info/WHEEL
cookiecutter_x-0.1.4.dist-info/entry_points.txt
cookiecutter_x-0.1.4.dist-info/top_level.txt
cookiecutter_x-0.1.4.dist-info/RECORD
