Metadata-Version: 2.1
Name: cookiecutter-x
Version: 0.1.4
Summary: Cookiecutter eXtended
Home-page: https://github.com/fahadshaon/cookiecutter-x
Author: Fahad Shaon
Author-email: fs@shaon.dev
License: http://www.apache.org/licenses/LICENSE-2.0
Project-URL: Bug Tracker, https://github.com/fahadshaon/cookiecutter-x/issues
Keywords: cookiecutter-x,cookiecutter,projects,project templates,Jinja2,scaffolding,development
Classifier: Programming Language :: Python :: 3
Classifier: License :: OSI Approved :: Apache Software License
Classifier: Operating System :: OS Independent
Requires-Python: >=3.6
License-File: LICENSE.txt
Requires-Dist: cached-property
Requires-Dist: cookiecutter
Requires-Dist: click
Requires-Dist: coloredlogs
Requires-Dist: Jinja2
Requires-Dist: PyYaml
Requires-Dist: tabulate
Provides-Extra: test
Requires-Dist: coverage ; extra == 'test'
Requires-Dist: pyfakefs ; extra == 'test'
